deepfakeecg/__init__.py
deepfakeecg/deepfakeecg.py
deepfakeecg/checkpoints/g_stat.pt
deepfakeecg/models/__init__.py
deepfakeecg/models/pulse2pulse.py
deepfake_ecg-1.1.2.dist-info/LICENSE
deepfake_ecg-1.1.2.dist-info/METADATA
deepfake_ecg-1.1.2.dist-info/WHEEL
deepfake_ecg-1.1.2.dist-info/top_level.txt
deepfake_ecg-1.1.2.dist-info/RECORD
