Metadata-Version: 2.1
Name: deepfake-ecg
Version: 1.1.2
Summary: Unlimited 10-sec 8-leads Deep Fake ECG generator.
Home-page: https://github.com/vlbthambawita/deepfake-ecg
Author: Vajira Thambawita
Author-email: vlbthambawita@gmail.com
License: UNKNOWN
Platform: UNKNOWN
Classifier: Programming Language :: Python :: 3
Classifier: License :: OSI Approved :: MIT License
Classifier: Operating System :: OS Independent
Requires-Python: >=3.6
Requires-Dist: numpy
Requires-Dist: tqdm
Requires-Dist: pandas
